.codeclimate.yml
.travis.yml
MANIFEST.in
README.rst
pyproject.toml
setup.cfg
setup.py
docs/Makefile
docs/authors.rst
docs/conf.py
docs/index.rst
docs/installation.rst
docs/make.bat
docs/readme.rst
docs/reference.rst
docs/requirements.txt
docs/usage.rst
docs/.build/doctrees/authors.doctree
docs/.build/doctrees/environment.pickle
docs/.build/doctrees/index.doctree
docs/.build/doctrees/installation.doctree
docs/.build/doctrees/readme.doctree
docs/.build/doctrees/reference.doctree
docs/.build/doctrees/usage.doctree
docs/.build/html/.buildinfo
docs/.build/html/authors.html
docs/.build/html/genindex-all.html
docs/.build/html/genindex.html
docs/.build/html/index.html
docs/.build/html/installation.html
docs/.build/html/objects.inv
docs/.build/html/readme.html
docs/.build/html/reference.html
docs/.build/html/search.html
docs/.build/html/searchindex.js
docs/.build/html/usage.html
docs/.build/html/_sources/authors.rst.txt
docs/.build/html/_sources/index.rst.txt
docs/.build/html/_sources/installation.rst.txt
docs/.build/html/_sources/readme.rst.txt
docs/.build/html/_sources/reference.rst.txt
docs/.build/html/_sources/usage.rst.txt
docs/.build/html/_static/ajax-loader.gif
docs/.build/html/_static/basic.css
docs/.build/html/_static/comment-bright.png
docs/.build/html/_static/comment-close.png
docs/.build/html/_static/comment.png
docs/.build/html/_static/doctools.js
docs/.build/html/_static/documentation_options.js
docs/.build/html/_static/down-pressed.png
docs/.build/html/_static/down.png
docs/.build/html/_static/file.png
docs/.build/html/_static/jquery-3.2.1.js
docs/.build/html/_static/jquery.js
docs/.build/html/_static/language_data.js
docs/.build/html/_static/minus.png
docs/.build/html/_static/plus.png
docs/.build/html/_static/pygments.css
docs/.build/html/_static/searchtools.js
docs/.build/html/_static/underscore-1.3.1.js
docs/.build/html/_static/underscore.js
docs/.build/html/_static/up-pressed.png
docs/.build/html/_static/up.png
docs/.build/html/_static/websupport.js
src/GeoNDT.egg-info/PKG-INFO
src/GeoNDT.egg-info/SOURCES.txt
src/GeoNDT.egg-info/dependency_links.txt
src/GeoNDT.egg-info/entry_points.txt
src/GeoNDT.egg-info/not-zip-safe
src/GeoNDT.egg-info/requires.txt
src/GeoNDT.egg-info/top_level.txt
