Metadata-Version: 2.1
Name: GeoNDT
Version: 0.4.0
Summary: GeoNDT: a fast general-purpose computational tool for geotechnical non-destructive testing applications
Home-page: https://geondt.readthedocs.io/en/latest
Author: Hongwei Liu; Pooneh Maghoul; Guillaume Mantelet; Ahmed Shalaby
Author-email: liuh3429@myumanitoba.ca
License: MIT
Download-URL: https://github.com/Siglab-code/GeoNDT
Keywords: GeoNDT,Geophysics,geotechnical earthquake engineering,non-destructive testing,dispersion,multiphase geomaterials,spectral element,seismic tests,ultrasonic
Platform: UNKNOWN
Classifier: Intended Audience :: Science/Research
Classifier: License :: OSI Approved :: MIT License
Classifier: Programming Language :: Fortran
Classifier: Programming Language :: Python
Classifier: Programming Language :: Python :: 3.7
Classifier: Programming Language :: Python :: 3.8
Classifier: Programming Language :: Python :: Implementation :: CPython
Classifier: Topic :: Scientific/Engineering :: Physics
Classifier: Topic :: Utilities
Requires-Python: >= 3.7
